{
    "_links": {
        "self": {
            "href": "https://us.api.blizzard.com/data/wow/achievement/12832?namespace=static-11.1.5_60179-us"
        }
    },
    "id": 12832,
    "category": {
        "key": {
            "href": "https://us.api.blizzard.com/data/wow/achievement-category/15285?namespace=static-11.1.5_60179-us"
        },
        "name": "Battle Dungeon",
        "id": 15285
    },
    "name": "Heroic: Freehold",
    "description": "Defeat Harlan Sweete in Freehold on Heroic difficulty or higher.",
    "points": 10,
    "is_account_wide": false,
    "criteria": {
        "id": 67819,
        "description": "Freehold - Heroic Harlan",
        "amount": 0
    },
    "prerequisite_achievement": {
        "key": {
            "href": "https://us.api.blizzard.com/data/wow/achievement/12831?namespace=static-11.1.5_60179-us"
        },
        "name": "Freehold",
        "id": 12831
    },
    "next_achievement": {
        "key": {
            "href": "https://us.api.blizzard.com/data/wow/achievement/12999?namespace=static-11.1.5_60179-us"
        },
        "name": "Mythic: Freehold Guild Run",
        "id": 12999
    },
    "media": {
        "key": {
            "href": "https://us.api.blizzard.com/data/wow/media/achievement/12832?namespace=static-11.1.5_60179-us"
        },
        "id": 12832
    },
    "display_order": 4
}