{
    "_links": {
        "self": {
            "href": "https://us.api.blizzard.com/data/wow/achievement/13385?namespace=static-11.1.5_60179-us"
        }
    },
    "id": 13385,
    "category": {
        "key": {
            "href": "https://us.api.blizzard.com/data/wow/achievement-category/15259?namespace=static-11.1.5_60179-us"
        },
        "name": "Appearances",
        "id": 15259
    },
    "name": "Daz'aling Attire",
    "description": "Collect an armor set from the Battle of Dazar'alor.",
    "points": 10,
    "is_account_wide": true,
    "criteria": {
        "id": 72398,
        "description": "Collect a Tier 23 Set on at least 1 class.",
        "amount": 1
    },
    "media": {
        "key": {
            "href": "https://us.api.blizzard.com/data/wow/media/achievement/13385?namespace=static-11.1.5_60179-us"
        },
        "id": 13385
    },
    "display_order": 41
}